<?xml version="1.0" encoding="UTF-8"?>
<OpenSearchDescription xmlns="http://a9.com/-/spec/opensearch/1.1/"
                       xmlns:moz="http://www.mozilla.org/2006/browser/search/">
  <ShortName>Search Router</ShortName>
  <Description>Search Router with Bangs!</Description>
  <InputEncoding>UTF-8</InputEncoding>
  <Url type="text/html" method="get" template="https://searchrouter.app/?q={searchTerms}"/>
  <Url type="application/x-suggestions+json" method="get" template="https://suggestqueries.google.com/complete/search?client=firefox&q={searchTerms}"/>
  <moz:SearchForm>https://searchrouter.app/</moz:SearchForm>
</OpenSearchDescription>
